<?xml version="1.0" encoding="utf-8" ?>
<dwsync>
<file name="node-term_node-term_data-large.png" server="ftp.gesiod-info.1gb.ua/http/" local="129386832000000000" remote="129386832000000000" />
<file name="node-term_node-term_data.png" server="ftp.gesiod-info.1gb.ua/http/" local="129386832000000000" remote="129386832000000000" />
<file name="overview-ui-large.png" server="ftp.gesiod-info.1gb.ua/http/" local="129386832000000000" remote="129386832000000000" />
<file name="overview-ui-small.png" server="ftp.gesiod-info.1gb.ua/http/" local="129386832000000000" remote="129386832000000000" />
<file name="style-breakdown-large.png" server="ftp.gesiod-info.1gb.ua/http/" local="129386832000000000" remote="129386832000000000" />
<file name="style-breakdown.png" server="ftp.gesiod-info.1gb.ua/http/" local="129386832000000000" remote="129386832000000000" />
<file name="views1-admin-large.png" server="ftp.gesiod-info.1gb.ua/http/" local="129386832000000000" remote="129386832000000000" />
<file name="views1-admin.png" server="ftp.gesiod-info.1gb.ua/http/" local="129386832000000000" remote="129386832000000000" />
<file name="views1-changeviewtype-large.png" server="ftp.gesiod-info.1gb.ua/http/" local="129386832000000000" remote="129386832000000000" />
<file name="views1-changeviewtype.png" server="ftp.gesiod-info.1gb.ua/http/" local="129386832000000000" remote="129386832000000000" />
<file name="views2-addaview-large.png" server="ftp.gesiod-info.1gb.ua/http/" local="129386832000000000" remote="129386832000000000" />
<file name="views2-addaview.png" server="ftp.gesiod-info.1gb.ua/http/" local="129386832000000000" remote="129386832000000000" />
<file name="views2-adddisplay-large.png" server="ftp.gesiod-info.1gb.ua/http/" local="129386832000000000" remote="129386832000000000" />
<file name="views2-adddisplay.png" server="ftp.gesiod-info.1gb.ua/http/" local="129386832000000000" remote="129386832000000000" />
<file name="views2-addfields-large.png" server="ftp.gesiod-info.1gb.ua/http/" local="129386832000000000" remote="129386832000000000" />
<file name="views2-addfields.png" server="ftp.gesiod-info.1gb.ua/http/" local="129386832000000000" remote="129386832000000000" />
<file name="views2-addfieldsajax-large.png" server="ftp.gesiod-info.1gb.ua/http/" local="129386832000000000" remote="129386832000000000" />
<file name="views2-addfieldsajax.png" server="ftp.gesiod-info.1gb.ua/http/" local="129386832000000000" remote="129386832000000000" />
<file name="views2-admin-large.png" server="ftp.gesiod-info.1gb.ua/http/" local="129386832000000000" remote="129386832000000000" />
<file name="views2-admin.png" server="ftp.gesiod-info.1gb.ua/http/" local="129386832000000000" remote="129386832000000000" />
<file name="views2-changedisplaystyle-large.png" server="ftp.gesiod-info.1gb.ua/http/" local="129386832000000000" remote="129386832000000000" />
<file name="views2-changedisplaystyle.png" server="ftp.gesiod-info.1gb.ua/http/" local="129386832000000000" remote="129386832000000000" />
<file name="views2-fieldspreview-large.png" server="ftp.gesiod-info.1gb.ua/http/" local="129386832000000000" remote="129386832000000000" />
<file name="views2-fieldspreview.png" server="ftp.gesiod-info.1gb.ua/http/" local="129386832000000000" remote="129386832000000000" />
<file name="views2-newview-large.png" server="ftp.gesiod-info.1gb.ua/http/" local="129386832000000000" remote="129386832000000000" />
<file name="views2-newview.png" server="ftp.gesiod-info.1gb.ua/http/" local="129386832000000000" remote="129386832000000000" />
<file name="views2-rearrangefields-large.png" server="ftp.gesiod-info.1gb.ua/http/" local="129386832000000000" remote="129386832000000000" />
<file name="views2-rearrangefields.png" server="ftp.gesiod-info.1gb.ua/http/" local="129386832000000000" remote="129386832000000000" />
<file name="views2-tablestyle-large.png" server="ftp.gesiod-info.1gb.ua/http/" local="129386832000000000" remote="129386832000000000" />
<file name="views2-tablestyle.png" server="ftp.gesiod-info.1gb.ua/http/" local="129386832000000000" remote="129386832000000000" />
</dwsync>