<?xml version="1.0" encoding="utf-8" ?>
<dwsync>
<file name="CHANGELOG.txt" server="ftp.gesiod-info.1gb.ua/http/" local="129451253400000000" remote="129451253400000000" />
<file name="CREDITS.txt" server="ftp.gesiod-info.1gb.ua/http/" local="129451253400000000" remote="129451253400000000" />
<file name="LICENSE.txt" server="ftp.gesiod-info.1gb.ua/http/" local="129451253400000000" remote="129451253400000000" />
<file name="README.txt" server="ftp.gesiod-info.1gb.ua/http/" local="129451253400000000" remote="129451253400000000" />
<file name="uc_attribute_cck.admin.inc" server="ftp.gesiod-info.1gb.ua/http/" local="129451253400000000" remote="129451253400000000" />
<file name="uc_attribute_cck.info" server="ftp.gesiod-info.1gb.ua/http/" local="129451253400000000" remote="129451253400000000" />
<file name="uc_attribute_cck.install" server="ftp.gesiod-info.1gb.ua/http/" local="129451253400000000" remote="129451253400000000" />
<file name="uc_attribute_cck.module" server="ftp.gesiod-info.1gb.ua/http/" local="129451253400000000" remote="129451253400000000" />
</dwsync>